py3d/__init__.py
py3d/core.py
py3d/rendering.py
py3d/utils.py
py3d/__pycache__/__init__.cpython-312.pyc
py3d/__pycache__/core.cpython-312.pyc
py3d/__pycache__/rendering.cpython-312.pyc
py3d/__pycache__/utils.cpython-312.pyc
py3d/data/large_model1.mtl
py3d/data/large_model1.obj
py3d/data/large_model2.mtl
py3d/data/large_model2.obj
py3d/data/textures/texture1.png
py3d/data/textures/texture2.png
py3d/models/__init__.py
py3d/models/geometry.py
py3d/models/textures.py
py3d/models/__pycache__/__init__.cpython-312.pyc
py3d/models/__pycache__/geometry.cpython-312.pyc
py3d/models/__pycache__/textures.cpython-312.pyc
tests/__init__.py
tests/test_core.py
py3drj-0.1.dist-info/METADATA
py3drj-0.1.dist-info/WHEEL
py3drj-0.1.dist-info/top_level.txt
py3drj-0.1.dist-info/RECORD
