Metadata-Version: 2.1
Name: py3drj
Version: 0.1
Summary: A simple 3D rendering Python library
Home-page: https://github.com/AlexRepre/Py3DRJ
Author: Alex Repre
Author-email: cblackmidis@gmail.com
Classifier: Programming Language :: Python :: 3
Classifier: License :: OSI Approved :: MIT License
Classifier: Operating System :: OS Independent
Requires-Python: >=3.6
Requires-Dist: numpy
Requires-Dist: matplotlib
Requires-Dist: Pillow
